README
setup.py
closure_depresolver/__init__.py
closure_depresolver/clresolve.py
closure_depresolver/source.py
closure_depresolver/treescan.py
closure_depresolver.egg-info/PKG-INFO
closure_depresolver.egg-info/SOURCES.txt
closure_depresolver.egg-info/dependency_links.txt
closure_depresolver.egg-info/entry_points.txt
closure_depresolver.egg-info/requires.txt
closure_depresolver.egg-info/top_level.txt