Metadata-Version: 1.0
Name: closure-depresolver
Version: 0.0.1
Summary: Scans your CL files to help you correctly goog.providing and goog.requiring your classes.
Home-page: https://github.com/knutwalker/closure_depresolver
Author: Paul Horn
Author-email: knutwalker@gmail.com
License: GPLv3
Platform: UNKNOWN
